ghoststream/__init__.py
ghoststream/__main__.py
ghoststream/client.py
ghoststream/config.py
ghoststream/launcher.py
ghoststream/logging_config.py
ghoststream/models.py
ghoststream/api/__init__.py
ghoststream/api/app.py
ghoststream/api/middleware.py
ghoststream/api/websocket.py
ghoststream/api/routes/__init__.py
ghoststream/api/routes/health.py
ghoststream/api/routes/stream.py
ghoststream/api/routes/transcode.py
ghoststream/discovery/__init__.py
ghoststream/discovery/browser.py
ghoststream/discovery/ghosthub.py
ghoststream/discovery/service.py
ghoststream/hardware/__init__.py
ghoststream/hardware/detector.py
ghoststream/hardware/models.py
ghoststream/jobs/__init__.py
ghoststream/jobs/manager.py
ghoststream/jobs/models.py
ghoststream/jobs/stats.py
ghoststream/transcoding/__init__.py
ghoststream/transcoding/adaptive.py
ghoststream/transcoding/commands.py
ghoststream/transcoding/constants.py
ghoststream/transcoding/encoders.py
ghoststream/transcoding/engine.py
ghoststream/transcoding/error_classifier.py
ghoststream/transcoding/ffmpeg_runner.py
ghoststream/transcoding/filters.py
ghoststream/transcoding/hls.py
ghoststream/transcoding/job_context.py
ghoststream/transcoding/models.py
ghoststream/transcoding/probe.py
ghoststream/transcoding/scheduler.py
ghoststream/transcoding/worker.py
ghoststream-1.2.2.dist-info/licenses/LICENSE
ghoststream-1.2.2.dist-info/METADATA
ghoststream-1.2.2.dist-info/WHEEL
ghoststream-1.2.2.dist-info/entry_points.txt
ghoststream-1.2.2.dist-info/top_level.txt
ghoststream-1.2.2.dist-info/RECORD
