Metadata-Version: 2.4
Name: ghoststream
Version: 1.2.2
Summary: Open Source Cross-Platform Transcoding Service & SDK
Home-page: https://github.com/BleedingXiko/GhostStream
Author: GhostStream Contributors
Classifier: Development Status :: 4 - Beta
Classifier: Intended Audience :: Developers
Classifier: Intended Audience :: System Administrators
Classifier: License :: OSI Approved :: MIT License
Classifier: Operating System :: OS Independent
Classifier: Programming Language :: Python :: 3
Classifier: Programming Language :: Python :: 3.10
Classifier: Programming Language :: Python :: 3.11
Classifier: Programming Language :: Python :: 3.12
Classifier: Topic :: Multimedia :: Video :: Conversion
Classifier: Framework :: FastAPI
Requires-Python: >=3.10
License-File: LICENSE
Requires-Dist: httpx>=0.27.0
Requires-Dist: zeroconf>=0.131.0
Requires-Dist: websockets>=12.0
Provides-Extra: server
Requires-Dist: fastapi>=0.109.0; extra == "server"
Requires-Dist: uvicorn[standard]>=0.27.0; extra == "server"
Requires-Dist: python-multipart>=0.0.9; extra == "server"
Requires-Dist: pyyaml>=6.0.1; extra == "server"
Requires-Dist: pydantic>=2.6.0; extra == "server"
Requires-Dist: pydantic-settings>=2.2.0; extra == "server"
Requires-Dist: aiofiles>=23.2.1; extra == "server"
Requires-Dist: asyncio-throttle>=1.0.2; extra == "server"
Requires-Dist: python-json-logger>=2.0.7; extra == "server"
Requires-Dist: psutil>=5.9.7; extra == "server"
Provides-Extra: all
Requires-Dist: httpx>=0.27.0; extra == "all"
Requires-Dist: zeroconf>=0.131.0; extra == "all"
Requires-Dist: websockets>=12.0; extra == "all"
Requires-Dist: fastapi>=0.109.0; extra == "all"
Requires-Dist: uvicorn[standard]>=0.27.0; extra == "all"
Requires-Dist: python-multipart>=0.0.9; extra == "all"
Requires-Dist: pyyaml>=6.0.1; extra == "all"
Requires-Dist: pydantic>=2.6.0; extra == "all"
Requires-Dist: pydantic-settings>=2.2.0; extra == "all"
Requires-Dist: aiofiles>=23.2.1; extra == "all"
Requires-Dist: asyncio-throttle>=1.0.2; extra == "all"
Requires-Dist: python-json-logger>=2.0.7; extra == "all"
Requires-Dist: psutil>=5.9.7; extra == "all"
Provides-Extra: dev
Requires-Dist: pytest>=7.4.0; extra == "dev"
Requires-Dist: pytest-asyncio>=0.23.0; extra == "dev"
Dynamic: author
Dynamic: classifier
Dynamic: description
Dynamic: description-content-type
Dynamic: home-page
Dynamic: license-file
Dynamic: provides-extra
Dynamic: requires-dist
Dynamic: requires-python
Dynamic: summary
